EJ1/verilog_ejb/src/ff.v
module ff (data, clk, reset, q);

        input data, clk, reset ; 

        output q;
        reg q=0;

        always @ ( posedge clk or negedge reset)
            if (reset) begin
                q <= 1'b0;
            end else begin
                q <= data;
            end
endmodule

EJ2/verilog/src/ej2.v
module ej2a(w, clk, out);
	input w,clk;
	output out;
	
	wire conn1, conn2, conn3, conn4, conn5, conn6, conn7, conn8;
	wire Q1, Q2, Q3;
	wire D1, D2, D3;

	assign conn1 = !(conn7 && conn5); //
	assign conn2 = !(conn5 && conn4);//
	assign conn3 = !( (!Q3) && (!conn6));//
	assign conn4 = !(Q1 && (!Q2) && w);//
	assign conn5 = !(Q2 && (!Q1) && conn8);//
	assign conn6 = !(Q2 && Q1 && w); //
	assign conn7 = !(w && (!Q3) && (!Q2) && (!Q1));// 
	assign conn8 = !w; //
	assign D3 = conn3;
	assign D2 = conn2;
	assign D1 = conn1;

	assign out = Q3;

	ff ff_my1(D1, clk, 1'b0, Q1);
	ff ff_my2(D2, clk, 1'b0, Q2);
	ff ff_my3(D3, clk, 1'b0, Q3);
endmodule

EJ2/verilog/src/testing.v
`timescale 1ns / 1ps

module testing;	
	reg w,  clk;
	output out;
		
	ej2a ej2(w, clk, out);

	initial begin
		$dumpfile("output.vcd");
		$dumpvars(0,testing);

		#1 w = 1;
		#1 clk = 0;
		#1 clk = 1;
		
		#1 w = 1;
		#1 clk = 0;
		#1 clk = 1;		
			
		#1 w = 0;
		#1 clk = 0;
		#1 clk = 1;

		#1 w = 0;
		#1 clk = 0;
		#1 clk = 1;
		
		#1 w = 1;
		#1 clk = 0;
		#1 clk = 1;

		#1 w = 1;
		#1 clk = 0;
		#1 clk = 1;
		
		#1 w = 1;
		#1 clk = 0;
		#1 clk = 1;

		#1 w = 0;
		#1 clk = 0;
		#1 clk = 1;

		#1 w = 1;
		#1 clk = 0;
		#1 clk = 1;


		#3
		$finish;
	end

endmodule

EJ2/verilog/output.vcd
$date
	Wed Nov 14 18:09:53 2018
$end
$version
	Icarus Verilog
$end
$timescale
	1ps
$end
$scope module testing $end
$var wire 1 ! out $end
$var reg 1 " clk $end
$var reg 1 # w $end
$scope module ej2 $end
$var wire 1 $ D1 $end
$var wire 1 % D2 $end
$var wire 1 & D3 $end
$var wire 1 " clk $end
$var wire 1 ! out $end
$var wire 1 # w $end
$var wire 1 ' conn8 $end
$var wire 1 ( conn7 $end
$var wire 1 ) conn6 $end
$var wire 1 * conn5 $end
$var wire 1 + conn4 $end
$var wire 1 , conn3 $end
$var wire 1 - conn2 $end
$var wire 1 . conn1 $end
$var wire 1 / Q3 $end
$var wire 1 0 Q2 $end
$var wire 1 1 Q1 $end
$scope module ff_my1 $end
$var wire 1 " clk $end
$var wire 1 $ data $end
$var wire 1 2 reset $end
$var reg 1 1 q $end
$upscope $end
$scope module ff_my2 $end
$var wire 1 " clk $end
$var wire 1 % data $end
$var wire 1 3 reset $end
$var reg 1 0 q $end
$upscope $end
$scope module ff_my3 $end
$var wire 1 " clk $end
$var wire 1 & data $end
$var wire 1 4 reset $end
$var reg 1 / q $end
$upscope $end
$upscope $end
$upscope $end
$enddefinitions $end
#0
$dumpvars
04
03
02
01
00
0/
x.
0-
1,
1+
1*
1)
x(
x'
1&
0%
x$
x#
x"
0!
$end
#1000
1$
1.
0(
0'
1#
#2000
0"
#3000
1%
1-
0$
0.
0+
1(
11
1!
1/
1"
#5000
0"
#6000
0%
0-
1+
01
10
1"
#7000
1%
1-
1$
1.
0*
1'
0#
#8000
0"
#9000
0%
0-
0$
0.
1*
11
1"
#11000
0"
#12000
01
00
1"
#13000
0'
1#
#14000
0"
#15000
1"
#17000
0"
#18000
1"
#20000
0"
#21000
1"
#22000
1'
0#
#23000
0"
#24000
1"
#25000
0'
1#
