EJ1/verilog_ejb/src/ff.v
module ff (data, clk, reset, q);

        input data, clk, reset ; 

        output q;
        reg q=0;

        always @ ( posedge clk or negedge reset)
            if (reset) begin
                q <= 1'b0;
            end else begin
                q <= data;
            end
endmodule

EJ3/verilog/src/ej3.v
module ej3a(w, clk, OUT);
	input w, clk;
	output OUT;
	
	wire conn1, conn2, conn3, conn4;
	wire D1, D2;
	wire Q1, Q2;
	
	ff ff1(D1, clk, 1'b0, Q1);
	ff ff2(D2, clk, 1'b0, Q2);

	assign conn4 = ((!Q2) && (!Q1) && w);
	assign conn2 = !(Q2 && w);
	assign conn3 = !(Q1 && w);

	assign conn1 = !(conn2 && conn3);

	assign D1 = conn4;
	assign D2 = conn1;

	assign OUT = Q1;

endmodule

EJ3/verilog/src/testing.v
`timescale 1ns / 1ps

module testing;	
	reg w,  clk;
	output out;
		
	ej3a ej3(w, clk, out);

	initial begin
		$dumpfile("output.vcd");
		$dumpvars(0,testing);

		#1 w = 1;
		#1 clk = 0;
		#1 clk = 1;
		
		#1 w = 0;
		#1 clk = 0;
		#1 clk = 1;

		#1 w = 0;
		#1 clk = 0;
		#1 clk = 1;

		#1 w = 1;
		#1 clk = 0;
		#1 clk = 1;
		
		#1 w = 1;
		#1 clk = 0;
		#1 clk = 1;
		
		#3
 		$finish;
	end

endmodule

EJ3/verilog/output.vcd
$date
	Wed Nov 14 18:32:13 2018
$end
$version
	Icarus Verilog
$end
$timescale
	1ps
$end
$scope module testing $end
$var wire 1 ! out $end
$var reg 1 " clk $end
$var reg 1 # w $end
$scope module ej3 $end
$var wire 1 $ D1 $end
$var wire 1 % D2 $end
$var wire 1 ! OUT $end
$var wire 1 " clk $end
$var wire 1 & conn4 $end
$var wire 1 # w $end
$var wire 1 ' conn3 $end
$var wire 1 ( conn2 $end
$var wire 1 ) conn1 $end
$var wire 1 * Q2 $end
$var wire 1 + Q1 $end
$scope module ff1 $end
$var wire 1 " clk $end
$var wire 1 $ data $end
$var wire 1 , reset $end
$var reg 1 + q $end
$upscope $end
$scope module ff2 $end
$var wire 1 " clk $end
$var wire 1 % data $end
$var wire 1 - reset $end
$var reg 1 * q $end
$upscope $end
$upscope $end
$upscope $end
$enddefinitions $end
#0
$dumpvars
0-
0,
0+
0*
0)
1(
1'
x&
0%
x$
x#
x"
0!
$end
#1000
1$
1&
1#
#2000
0"
#3000
0$
0&
1%
1)
0'
1!
1+
1"
#4000
0%
0)
1'
0#
#5000
0"
#6000
0!
0+
1"
#8000
0"
#9000
1"
#10000
1$
1&
1#
#11000
0"
#12000
0$
0&
1%
1)
0'
1!
1+
1"
#14000
0"
#15000
1'
0(
0!
0+
1*
1"
